KubernetesZhongwenWendang/README.md
KubernetesZhongwenWendang/__init__.py
KubernetesZhongwenWendang/__main__.py
KubernetesZhongwenWendang/file.epub
KubernetesZhongwenWendang/index.html
KubernetesZhongwenWendang/css/__init__.py
KubernetesZhongwenWendang/css/annotations.css
KubernetesZhongwenWendang/css/main.css
KubernetesZhongwenWendang/css/normalize.css
KubernetesZhongwenWendang/css/popup.css
KubernetesZhongwenWendang/font/__init__.py
KubernetesZhongwenWendang/font/fontello.eot
KubernetesZhongwenWendang/font/fontello.svg
KubernetesZhongwenWendang/font/fontello.ttf
KubernetesZhongwenWendang/font/fontello.woff
KubernetesZhongwenWendang/img/__init__.py
KubernetesZhongwenWendang/img/annotator-glyph-sprite.png
KubernetesZhongwenWendang/img/annotator-icon-sprite.png
KubernetesZhongwenWendang/img/apple-touch-icon.png
KubernetesZhongwenWendang/img/cancelfullscreen.png
KubernetesZhongwenWendang/img/close.png
KubernetesZhongwenWendang/img/fullscreen.png
KubernetesZhongwenWendang/img/loader.gif
KubernetesZhongwenWendang/img/menu-icon.png
KubernetesZhongwenWendang/img/save.png
KubernetesZhongwenWendang/img/saved.png
KubernetesZhongwenWendang/img/settings-s.png
KubernetesZhongwenWendang/img/settings.png
KubernetesZhongwenWendang/img/star.png
KubernetesZhongwenWendang/js/__init__.py
KubernetesZhongwenWendang/js/epub.js
KubernetesZhongwenWendang/js/epub.min.js
KubernetesZhongwenWendang/js/epub.min.map
KubernetesZhongwenWendang/js/hooks.min.js
KubernetesZhongwenWendang/js/hooks.min.map
KubernetesZhongwenWendang/js/reader.js
KubernetesZhongwenWendang/js/reader.js.map
KubernetesZhongwenWendang/js/reader.min.js
KubernetesZhongwenWendang/js/reader.min.map
KubernetesZhongwenWendang/js/hooks/__init__.py
KubernetesZhongwenWendang/js/hooks/extensions/__init__.py
KubernetesZhongwenWendang/js/hooks/extensions/highlight.js
KubernetesZhongwenWendang/js/libs/__init__.py
KubernetesZhongwenWendang/js/libs/jquery.min.js
KubernetesZhongwenWendang/js/libs/localforage.min.js
kubernetes_zhongwen_wendang-2024.3.3.0.dist-info/METADATA
kubernetes_zhongwen_wendang-2024.3.3.0.dist-info/WHEEL
kubernetes_zhongwen_wendang-2024.3.3.0.dist-info/entry_points.txt
kubernetes_zhongwen_wendang-2024.3.3.0.dist-info/top_level.txt
kubernetes_zhongwen_wendang-2024.3.3.0.dist-info/RECORD
